tartpy/__init__.py
tartpy/erlang_challenge.py
tartpy/eventloop.py
tartpy/example.py
tartpy/factorial.py
tartpy/membrane.py
tartpy/network.py
tartpy/runtime.py
tartpy/serial.py
tartpy/singleton.py
tartpy/tools.py
tartpy/tests/__init__.py
tartpy/tests/test_actor.py
tartpy/tests/test_membrane.py
tartpy-0.2.1.dist-info/DESCRIPTION.rst
tartpy-0.2.1.dist-info/METADATA
tartpy-0.2.1.dist-info/metadata.json
tartpy-0.2.1.dist-info/RECORD
tartpy-0.2.1.dist-info/top_level.txt
tartpy-0.2.1.dist-info/WHEEL
