Metadata-Version: 2.0
Name: tartpy
Version: 0.2.1
Summary: Tiny Actor Run-Time in Python.
Home-page: http://github.com/waltermoreira/tartpy
Author: Walter Moreira
Author-email: walter@waltermoreira.net
License: MIT
Platform: UNKNOWN
Requires-Dist: pytest (>=2.4)
Requires-Dist: Logbook
